{
  "_surface": {
    "generated_at": "2026-07-21T00:52:39Z",
    "repo_head": "1ef3001"
  },
  "manifest": {
    "totals": {
      "units": 31922,
      "rows": 158575,
      "batches": 18,
      "echo_groups": 566
    },
    "classes_count": 26,
    "machine_approved": {
      "units": 24375,
      "by_class": {
        "boundary-echo": 8654,
        "dangling-anchor-dropped": 6446,
        "bare-name-live-join": 4006,
        "ss10-isolation-completed": 4190,
        "ss10-ligature-suppressed": 745,
        "kern-channel-out-of-scope": 334
      }
    },
    "class_unit_count": {
      "boundary-echo": 10800,
      "dangling-anchor-dropped": 6506,
      "bare-name-live-join": 4404
    },
    "secondary_seams": {
      "units_with_markers": 2519,
      "seams_homed": 1040,
      "seams_homeless": 1696,
      "seams_suppressed_invisible": 0
    }
  },
  "built": {
    "human_units": 5201,
    "config_note_distribution": [
      [
        null,
        18822
      ],
      [
        "only under ss10",
        7344
      ],
      [
        "only under: default, ss02, ss05",
        46
      ],
      [
        "only when ss03 is off",
        1428
      ],
      [
        "only when ss03 is on",
        2180
      ],
      [
        "only when ss04 is off",
        997
      ],
      [
        "only when ss04 is on",
        1105
      ]
    ]
  },
  "audit": {
    "row_count": 158575,
    "units": 32994
  },
  "ink": {
    "machine_total": 17962,
    "non_identical": 15032,
    "by_class": {
      "boundary-echo": 7042,
      "dangling-anchor-dropped": 6914,
      "bare-name-live-join": 4006
    },
    "boundary_echo_exempt": 4441,
    "human_units": 10591,
    "batches": 36
  },
  "families": {
    "census": {
      "no-chain-gains": 212,
      "tea-it-xheight": 41,
      "oy-it-baseline": 18,
      "may-utter-gains": 110,
      "seam-loss-withdrawal": 565,
      "extension-non-summing": 411,
      "unmatched-misc": 478,
      "deferred-ss04": 561,
      "deferred-ss03": 535
    },
    "total": 2931
  }
}
